keyscore/__init__.py
keyscore/client.py
keyscore/models.py
keyscore_py-1.0.0.dist-info/licenses/LICENSE
keyscore_py-1.0.0.dist-info/METADATA
keyscore_py-1.0.0.dist-info/WHEEL
keyscore_py-1.0.0.dist-info/top_level.txt
keyscore_py-1.0.0.dist-info/RECORD
