Metadata-Version: 2.4
Name: keyscore-py
Version: 1.0.0
Summary: Python client for keysco.re API - Search and lookup data across multiple sources
Author-email: esson <esson@riseup.net>
Maintainer-email: esson <esson@riseup.net>
License: Apache-2.0
Project-URL: homepage, https://keysco.re/
Project-URL: repository, https://github.com/keysco-re/keyscore-py
Project-URL: documentation, https://docs.keysco.re/
Project-URL: bug-tracker, https://github.com/keysco-re/keyscore-py/issues
Keywords: keysco.re,api,client,osint,lookup,search,intelligence
Classifier: Development Status :: 4 - Beta
Classifier: Intended Audience :: Developers
Classifier: Intended Audience :: Information Technology
Classifier: License :: OSI Approved :: Apache Software License
Classifier: Operating System :: OS Independent
Classifier: Programming Language :: Python :: 3
Classifier: Programming Language :: Python :: 3.8
Classifier: Programming Language :: Python :: 3.9
Classifier: Programming Language :: Python :: 3.10
Classifier: Programming Language :: Python :: 3.11
Classifier: Programming Language :: Python :: 3.12
Classifier: Topic :: Internet :: WWW/HTTP :: Dynamic Content
Classifier: Topic :: Software Development :: Libraries :: Python Modules
Classifier: Topic :: System :: Networking
Requires-Python: >=3.8
License-File: LICENSE
Requires-Dist: requests>=2.31.0
Dynamic: license-file
